{
  "id": "ham-airport",
  "tipo": "aeropuerto",
  "nombre": "Aeropuerto de Hamburgo",
  "codigo_iata": "HAM",
  "direccion": {
    "calle": "Flughafenstr. 1-3",
    "ciudad": "Hamburgo",
    "codigo_postal": "22335",
    "pais": "Alemania",
    "coordenadas": {
      "lat": 53.6304,
      "lng": 9.9882
    },
    "maps_link": "https://www.google.com/maps?q=Hamburg+Airport+HAM"
  },
  "contacto": {
    "telefono": "+49 40 5075 0",
    "web": "https://www.hamburg-airport.de"
  },
  "reserva": {
    "codigo_reserva": "KL1753-2026",
    "confirmada": true,
    "nombre_titular": "Juan David",
    "plataforma": "KLM"
  },
  "fechas_estadia": {
    "entrada": "2026-07-27",
    "salida": "2026-07-27"
  },
  "horarios": {
    "atencion": "24h"
  },
  "clima_esperado": {
    "temperatura_promedio": "16°C - 22°C",
    "condiciones": "Parcialmente nublado, posibilidad de lluvia",
    "probabilidad_lluvia": "40%",
    "recomendacion_vestimenta": "Ropa ligera, chaqueta impermeable"
  },
  "idioma_principal": "Alemán, Inglés",
  "moneda_local": {
    "codigo": "EUR",
    "simbolo": "€",
    "tasa_referencia": "1 EUR ≈ 4500 COP"
  },
  "reglas_especiales": [
    "Revisión de pasaportes para viajeros extracomunitarios."
  ],
  "tiempo_estimado_visita": "2h",
  "notas_adicionales": "KLM llega a la Terminal 1 (T1). Para salir hacia la ciudad, tomar el S-Bahn línea S1 (dirección Wedel) hasta Reeperbahn (25 min)."
}